zmp_a2a_sdk/common/__init__.py
zmp_a2a_sdk/common/client/__init__.py
zmp_a2a_sdk/common/client/card_resolver.py
zmp_a2a_sdk/common/client/client.py
zmp_a2a_sdk/common/server/__init__.py
zmp_a2a_sdk/common/server/server.py
zmp_a2a_sdk/common/server/task_manager.py
zmp_a2a_sdk/common/server/utils.py
zmp_a2a_sdk/common/types.py
zmp_a2a_sdk/common/utils/in_memory_cache.py
zmp_a2a_sdk/common/utils/push_notification_auth.py
zmp_a2a_sdk-0.1.3.dist-info/METADATA
zmp_a2a_sdk-0.1.3.dist-info/WHEEL
zmp_a2a_sdk-0.1.3.dist-info/RECORD
